{
  "prod1": {
    "2026-03-31": {
      "status": "stock",
      "changed": false,
      "checked_at": "2026-03-31T12:54:00.870398+00:00",
      "price": "37.32",
      "price_changed": false
    }
  },
  "prod2": {
    "2026-03-31": {
      "status": "stock",
      "changed": false,
      "checked_at": "2026-03-31T12:54:10.664147+00:00",
      "price": "36.89",
      "price_changed": false
    }
  },
  "prod3": {
    "2026-03-31": {
      "status": "stock",
      "changed": false,
      "checked_at": "2026-03-31T12:54:14.783184+00:00",
      "price": "38.17",
      "price_changed": false
    }
  },
  "prod4": {
    "2026-03-31": {
      "status": "stock",
      "changed": false,
      "checked_at": "2026-03-31T12:54:18.355804+00:00",
      "price": "24.30",
      "price_changed": false
    }
  },
  "prod5": {
    "2026-03-31": {
      "status": "stock",
      "changed": false,
      "checked_at": "2026-03-31T12:54:21.468452+00:00",
      "price": "63.52",
      "price_changed": false
    }
  },
  "prod6": {
    "2026-03-31": {
      "status": "stock",
      "changed": false,
      "checked_at": "2026-03-31T12:54:24.524523+00:00",
      "price": "52.06",
      "price_changed": false
    }
  },
  "prod7": {
    "2026-03-31": {
      "status": "stock",
      "changed": false,
      "checked_at": "2026-03-31T12:54:27.544757+00:00",
      "price": "20.16",
      "price_changed": false
    }
  },
  "prod8": {
    "2026-03-31": {
      "status": "stock",
      "changed": false,
      "checked_at": "2026-03-31T12:54:34.396591+00:00",
      "price": "165.51",
      "price_changed": false
    }
  }
}